opencv_browser_camera/BrowserCamera.py
opencv_browser_camera/__init__.py
opencv_browser_camera/_templates/index.html
opencv_browser_camera-0.1.2.dist-info/LICENSE
opencv_browser_camera-0.1.2.dist-info/METADATA
opencv_browser_camera-0.1.2.dist-info/WHEEL
opencv_browser_camera-0.1.2.dist-info/RECORD
