Metadata-Version: 2.1
Name: opencv-browser-camera
Version: 0.1.2
Summary: 
Author: Séverin Férard
Author-email: severin.ferard@outlook.com
Requires-Python: >=3.12,<4.0
Classifier: Programming Language :: Python :: 3
Classifier: Programming Language :: Python :: 3.12
Requires-Dist: eventlet (>=0.36.1,<0.37.0)
Requires-Dist: flask (==2.2.0)
Requires-Dist: flask-socketio (>=5.3.7,<6.0.0)
Requires-Dist: imageio (>=2.35.1,<3.0.0)
Requires-Dist: opencv-python (>=4.10.0.84,<5.0.0.0)
Requires-Dist: pyopenssl (>=24.2.1,<25.0.0)
Requires-Dist: qrcode (>=7.4.2,<8.0.0)
Requires-Dist: werkzeug (==2.2.0)
